two_phase_galaxy_model/__init__.py
two_phase_galaxy_model/recipes/__init__.py
two_phase_galaxy_model/recipes/abc.py
two_phase_galaxy_model/recipes/galaxy_model.py
two_phase_galaxy_model/recipes/model.py
two_phase_galaxy_model/recipes/preproc.py
two_phase_galaxy_model/recipes/star_cluster_model.py
two_phase_galaxy_model/recipes/subclouds.py
two_phase_galaxy_model/recipes/subhalos.py
two_phase_galaxy_model/samples/__init__.py
two_phase_galaxy_model/samples/loaders.py
two_phase_galaxy_model/utils/__init__.py
two_phase_galaxy_model/utils/algorithm.py
two_phase_galaxy_model/utils/sampling.py
two_phase_galaxy_model-1.0.0.dist-info/LICENSE
two_phase_galaxy_model-1.0.0.dist-info/METADATA
two_phase_galaxy_model-1.0.0.dist-info/WHEEL
two_phase_galaxy_model-1.0.0.dist-info/top_level.txt
two_phase_galaxy_model-1.0.0.dist-info/RECORD
