Metadata-Version: 2.1
Name: two-phase-galaxy-model
Version: 1.0.0
Summary: A Two-Phase Scenario of Galaxy Formation
Author-email: Yangyao Chen <yangyaochen.astro@foxmail.com>
Project-URL: Repository, https://github.com/ChenYangyao/two-phase-galaxy-model.git
Classifier: Programming Language :: Python :: 3
Classifier: License :: OSI Approved :: MIT License
Classifier: Operating System :: OS Independent
Requires-Python: >=3.11
License-File: LICENSE
Requires-Dist: pyhipp
Requires-Dist: pyhipp-sims
Requires-Dist: pytest >=7.0.0
Requires-Dist: flake8
